mopidy_iris/__init__.py
mopidy_iris/core.py
mopidy_iris/ext.conf
mopidy_iris/frontend.py
mopidy_iris/handlers.py
mopidy_iris/mem.py
mopidy_iris/system.py
mopidy_iris/system.sh
mopidy_iris/static/app.css
mopidy_iris/static/app.css.map
mopidy_iris/static/app.js
mopidy_iris/static/app.js.map
mopidy_iris/static/app.min.css
mopidy_iris/static/app.min.js
mopidy_iris/static/app.min.js.LICENSE.txt
mopidy_iris/static/index.html
mopidy_iris/static/manifest.json
mopidy_iris/static/service-worker.js
mopidy_iris/static/assets/MaterialIcons-Regular.eot
mopidy_iris/static/assets/MaterialIcons-Regular.ttf
mopidy_iris/static/assets/MaterialIcons-Regular.woff
mopidy_iris/static/assets/MaterialIcons-Regular.woff2
mopidy_iris/static/assets/app-icon-invert.svg
mopidy_iris/static/assets/app-icon.svg
mopidy_iris/static/assets/app-icon_114.png
mopidy_iris/static/assets/app-icon_120.png
mopidy_iris/static/assets/app-icon_144.png
mopidy_iris/static/assets/app-icon_152.png
mopidy_iris/static/assets/app-icon_180.png
mopidy_iris/static/assets/app-icon_192.png
mopidy_iris/static/assets/app-icon_256.png
mopidy_iris/static/assets/app-icon_512.png
mopidy_iris/static/assets/app-icon_57.png
mopidy_iris/static/assets/app-icon_60.png
mopidy_iris/static/assets/app-icon_64.png
mopidy_iris/static/assets/app-icon_72.png
mopidy_iris/static/assets/app-icon_76.png
mopidy_iris/static/assets/blur.svg
mopidy_iris/static/assets/favicon.ico
mopidy_iris/static/assets/favicon.png
mopidy_iris/static/assets/favicon_error.png
mopidy_iris/static/assets/favicon_paused.png
mopidy_iris/static/assets/fontawesome-webfont.eot
mopidy_iris/static/assets/fontawesome-webfont.svg
mopidy_iris/static/assets/fontawesome-webfont.ttf
mopidy_iris/static/assets/fontawesome-webfont.woff
mopidy_iris/static/assets/fontawesome-webfont.woff2
mopidy_iris/static/assets/icon-no-bg-512.png
mopidy_iris/static/assets/logo.png
mopidy_iris/static/assets/logo.svg
mopidy_iris/static/assets/overpass-bold-webfont.woff
mopidy_iris-3.70.0.dist-info/licenses/LICENSE
mopidy_iris-3.70.0.dist-info/METADATA
mopidy_iris-3.70.0.dist-info/WHEEL
mopidy_iris-3.70.0.dist-info/entry_points.txt
mopidy_iris-3.70.0.dist-info/top_level.txt
mopidy_iris-3.70.0.dist-info/RECORD
