Metadata-Version: 2.4
Name: Mopidy-Iris
Version: 3.70.0
Summary: Fully-featured Mopidy frontend client
Home-page: https://github.com/jaedb/iris
Author: James Barnsley
Author-email: james@barnsley.nz
License: Apache License, Version 2.0
Classifier: Environment :: No Input/Output (Daemon)
Classifier: Intended Audience :: End Users/Desktop
Classifier: License :: OSI Approved :: Apache Software License
Classifier: Operating System :: OS Independent
Classifier: Programming Language :: Python :: 3
Classifier: Programming Language :: Python :: 3.7
Classifier: Programming Language :: Python :: 3.8
Classifier: Topic :: Multimedia :: Sound/Audio :: Players
Requires-Python: >=3.7
License-File: LICENSE
Requires-Dist: Mopidy>=3.0
Requires-Dist: Pykka>=2.0.1
Requires-Dist: setuptools
Provides-Extra: lint
Requires-Dist: black; extra == "lint"
Requires-Dist: check-manifest; extra == "lint"
Requires-Dist: flake8; extra == "lint"
Requires-Dist: flake8-bugbear; extra == "lint"
Requires-Dist: flake8-import-order; extra == "lint"
Requires-Dist: isort[pyproject]; extra == "lint"
Provides-Extra: release
Requires-Dist: twine; extra == "release"
Requires-Dist: wheel; extra == "release"
Provides-Extra: test
Requires-Dist: pytest; extra == "test"
Requires-Dist: pytest-cov; extra == "test"
Provides-Extra: dev
Requires-Dist: black; extra == "dev"
Requires-Dist: check-manifest; extra == "dev"
Requires-Dist: flake8; extra == "dev"
Requires-Dist: flake8-bugbear; extra == "dev"
Requires-Dist: flake8-import-order; extra == "dev"
Requires-Dist: isort[pyproject]; extra == "dev"
Requires-Dist: twine; extra == "dev"
Requires-Dist: wheel; extra == "dev"
Requires-Dist: pytest; extra == "dev"
Requires-Dist: pytest-cov; extra == "dev"
Dynamic: license-file
